[
    {
        "description": "",
        "group": {
            "description": "",
            "id": "2d2688011b934c258d366845e4780697",
            "is_error": false,
            "name": "\u0418\u043d\u0433\u0440\u0435\u0434\u0438\u0435\u043d\u0442\u044b"
        },
        "id": "171e70337e534ed7b7c49518e14be366",
        "is_error": false,
        "name": "\u041c\u0443\u043a\u0430 \u043f\u0448\u0435\u043d\u0438\u0447\u043d\u0430\u044f",
        "unit": {
            "base_unit": {
                "base_unit": null,
                "coefficient": 1,
                "description": "",
                "id": "7075b086851b4a4da0d61654e1614d14",
                "is_error": false,
                "name": "\u0433\u0440\u0430\u043c\u043c"
            },
            "coefficient": 1000,
            "description": "",
            "id": "570741618e994d1a845def2e717522d4",
            "is_error": false,
            "name": "\u043a\u0438\u043b\u043b\u043e\u0433\u0440\u0430\u043c\u043c"
        }
    },
    {
        "description": "",
        "group": {
            "description": "",
            "id": "2d2688011b934c258d366845e4780697",
            "is_error": false,
            "name": "\u0418\u043d\u0433\u0440\u0435\u0434\u0438\u0435\u043d\u0442\u044b"
        },
        "id": "c43bac7503734e2d8b0f75b1072b964d",
        "is_error": false,
        "name": "\u0421\u0430\u0445\u0430\u0440",
        "unit": {
            "base_unit": {
                "base_unit": null,
                "coefficient": 1,
                "description": "",
                "id": "7075b086851b4a4da0d61654e1614d14",
                "is_error": false,
                "name": "\u0433\u0440\u0430\u043c\u043c"
            },
            "coefficient": 1000,
            "description": "",
            "id": "570741618e994d1a845def2e717522d4",
            "is_error": false,
            "name": "\u043a\u0438\u043b\u043b\u043e\u0433\u0440\u0430\u043c\u043c"
        }
    },
    {
        "description": "",
        "group": {
            "description": "",
            "id": "2d2688011b934c258d366845e4780697",
            "is_error": false,
            "name": "\u0418\u043d\u0433\u0440\u0435\u0434\u0438\u0435\u043d\u0442\u044b"
        },
        "id": "9c8bf40c7ea249729aebbd2296ea0205",
        "is_error": false,
        "name": "\u0421\u043b\u0438\u0432\u043e\u0447\u043d\u043e\u0435 \u043c\u0430\u0441\u043b\u043e",
        "unit": {
            "base_unit": {
                "base_unit": null,
                "coefficient": 1,
                "description": "",
                "id": "7075b086851b4a4da0d61654e1614d14",
                "is_error": false,
                "name": "\u0433\u0440\u0430\u043c\u043c"
            },
            "coefficient": 1000,
            "description": "",
            "id": "570741618e994d1a845def2e717522d4",
            "is_error": false,
            "name": "\u043a\u0438\u043b\u043b\u043e\u0433\u0440\u0430\u043c\u043c"
        }
    },
    {
        "description": "",
        "group": {
            "description": "",
            "id": "2d2688011b934c258d366845e4780697",
            "is_error": false,
            "name": "\u0418\u043d\u0433\u0440\u0435\u0434\u0438\u0435\u043d\u0442\u044b"
        },
        "id": "e3e28f20fa4146aa903df5c8a06a2c38",
        "is_error": false,
        "name": "\u042f\u0439\u0446\u0430",
        "unit": {
            "base_unit": null,
            "coefficient": 1,
            "description": "",
            "id": "fec5f1c243eb46b6b5893d53736b5e47",
            "is_error": false,
            "name": "\u0448\u0442\u0443\u043a\u0430"
        }
    },
    {
        "description": "",
        "group": {
            "description": "",
            "id": "2d2688011b934c258d366845e4780697",
            "is_error": false,
            "name": "\u0418\u043d\u0433\u0440\u0435\u0434\u0438\u0435\u043d\u0442\u044b"
        },
        "id": "344777a372eb46cf80a0d939dfe60c40",
        "is_error": false,
        "name": "\u0412\u0430\u043d\u0438\u043b\u0438\u043d",
        "unit": {
            "base_unit": null,
            "coefficient": 1,
            "description": "",
            "id": "ea0f05b621084be1b533456e4058ccb1",
            "is_error": false,
            "name": "\u0433\u0440\u0430\u043c\u043c"
        }
    },
    {
        "description": "",
        "group": {
            "description": "",
            "id": "2d2688011b934c258d366845e4780697",
            "is_error": false,
            "name": "\u0418\u043d\u0433\u0440\u0435\u0434\u0438\u0435\u043d\u0442\u044b"
        },
        "id": "a842359eca984d35ba7962b9d2c800bf",
        "is_error": false,
        "name": "\u041a\u0443\u0440\u0438\u043d\u043e\u0435 \u0444\u0438\u043b\u0435",
        "unit": {
            "base_unit": {
                "base_unit": null,
                "coefficient": 1,
                "description": "",
                "id": "7075b086851b4a4da0d61654e1614d14",
                "is_error": false,
                "name": "\u0433\u0440\u0430\u043c\u043c"
            },
            "coefficient": 1000,
            "description": "",
            "id": "570741618e994d1a845def2e717522d4",
            "is_error": false,
            "name": "\u043a\u0438\u043b\u043b\u043e\u0433\u0440\u0430\u043c\u043c"
        }
    },
    {
        "description": "",
        "group": {
            "description": "",
            "id": "2d2688011b934c258d366845e4780697",
            "is_error": false,
            "name": "\u0418\u043d\u0433\u0440\u0435\u0434\u0438\u0435\u043d\u0442\u044b"
        },
        "id": "8765eaa729e1406fb856c7e8aec3a3d8",
        "is_error": false,
        "name": "\u0421\u0430\u043b\u0430\u0442 \u0420\u043e\u043c\u0430\u043d\u043e",
        "unit": {
            "base_unit": null,
            "coefficient": 1,
            "description": "",
            "id": "ea0f05b621084be1b533456e4058ccb1",
            "is_error": false,
            "name": "\u0433\u0440\u0430\u043c\u043c"
        }
    },
    {
        "description": "",
        "group": {
            "description": "",
            "id": "2d2688011b934c258d366845e4780697",
            "is_error": false,
            "name": "\u0418\u043d\u0433\u0440\u0435\u0434\u0438\u0435\u043d\u0442\u044b"
        },
        "id": "fddbf26976a04fcdb449469ff8dcff24",
        "is_error": false,
        "name": "\u0421\u044b\u0440 \u041f\u0430\u0440\u043c\u0435\u0437\u0430\u043d",
        "unit": {
            "base_unit": {
                "base_unit": null,
                "coefficient": 1,
                "description": "",
                "id": "7075b086851b4a4da0d61654e1614d14",
                "is_error": false,
                "name": "\u0433\u0440\u0430\u043c\u043c"
            },
            "coefficient": 1000,
            "description": "",
            "id": "570741618e994d1a845def2e717522d4",
            "is_error": false,
            "name": "\u043a\u0438\u043b\u043b\u043e\u0433\u0440\u0430\u043c\u043c"
        }
    },
    {
        "description": "",
        "group": {
            "description": "",
            "id": "2d2688011b934c258d366845e4780697",
            "is_error": false,
            "name": "\u0418\u043d\u0433\u0440\u0435\u0434\u0438\u0435\u043d\u0442\u044b"
        },
        "id": "48ff4fe9ec3f40959078b752b7f2df07",
        "is_error": false,
        "name": "\u0427\u0435\u0441\u043d\u043e\u043a",
        "unit": {
            "base_unit": {
                "base_unit": null,
                "coefficient": 1,
                "description": "",
                "id": "7075b086851b4a4da0d61654e1614d14",
                "is_error": false,
                "name": "\u0433\u0440\u0430\u043c\u043c"
            },
            "coefficient": 1000,
            "description": "",
            "id": "570741618e994d1a845def2e717522d4",
            "is_error": false,
            "name": "\u043a\u0438\u043b\u043b\u043e\u0433\u0440\u0430\u043c\u043c"
        }
    },
    {
        "description": "",
        "group": {
            "description": "",
            "id": "2d2688011b934c258d366845e4780697",
            "is_error": false,
            "name": "\u0418\u043d\u0433\u0440\u0435\u0434\u0438\u0435\u043d\u0442\u044b"
        },
        "id": "c384754fbb9a44f681154c216efea533",
        "is_error": false,
        "name": "\u0411\u0435\u043b\u044b\u0439 \u0445\u043b\u0435\u0431",
        "unit": {
            "base_unit": {
                "base_unit": null,
                "coefficient": 1,
                "description": "",
                "id": "7075b086851b4a4da0d61654e1614d14",
                "is_error": false,
                "name": "\u0433\u0440\u0430\u043c\u043c"
            },
            "coefficient": 1000,
            "description": "",
            "id": "570741618e994d1a845def2e717522d4",
            "is_error": false,
            "name": "\u043a\u0438\u043b\u043b\u043e\u0433\u0440\u0430\u043c\u043c"
        }
    },
    {
        "description": "",
        "group": {
            "description": "",
            "id": "2d2688011b934c258d366845e4780697",
            "is_error": false,
            "name": "\u0418\u043d\u0433\u0440\u0435\u0434\u0438\u0435\u043d\u0442\u044b"
        },
        "id": "62f08c7711e34e6ea6e4610a0bf777b1",
        "is_error": false,
        "name": "\u0421\u043e\u043b\u044c",
        "unit": {
            "base_unit": {
                "base_unit": null,
                "coefficient": 1,
                "description": "",
                "id": "7075b086851b4a4da0d61654e1614d14",
                "is_error": false,
                "name": "\u0433\u0440\u0430\u043c\u043c"
            },
            "coefficient": 1000,
            "description": "",
            "id": "570741618e994d1a845def2e717522d4",
            "is_error": false,
            "name": "\u043a\u0438\u043b\u043b\u043e\u0433\u0440\u0430\u043c\u043c"
        }
    },
    {
        "description": "",
        "group": {
            "description": "",
            "id": "2d2688011b934c258d366845e4780697",
            "is_error": false,
            "name": "\u0418\u043d\u0433\u0440\u0435\u0434\u0438\u0435\u043d\u0442\u044b"
        },
        "id": "f7f9de2ce9904c4fbb0dc97a096b87b5",
        "is_error": false,
        "name": "\u0427\u0435\u0440\u043d\u044b\u0439 \u043f\u0435\u0440\u0435\u0446",
        "unit": {
            "base_unit": null,
            "coefficient": 1,
            "description": "",
            "id": "ea0f05b621084be1b533456e4058ccb1",
            "is_error": false,
            "name": "\u0433\u0440\u0430\u043c\u043c"
        }
    },
    {
        "description": "",
        "group": {
            "description": "",
            "id": "2d2688011b934c258d366845e4780697",
            "is_error": false,
            "name": "\u0418\u043d\u0433\u0440\u0435\u0434\u0438\u0435\u043d\u0442\u044b"
        },
        "id": "4d8bf0f9c2564b228ae6cd7013984869",
        "is_error": false,
        "name": "\u041e\u043b\u0438\u0432\u043a\u043e\u0432\u043e\u0435 \u043c\u0430\u0441\u043b\u043e",
        "unit": {
            "base_unit": {
                "base_unit": null,
                "coefficient": 1,
                "description": "",
                "id": "f4f877c5af1e42508c303442b6aab3ad",
                "is_error": false,
                "name": "\u043c\u0438\u043b\u043b\u0438\u043b\u0438\u0442\u0440"
            },
            "coefficient": 1000,
            "description": "",
            "id": "52ef51fda1d34027b3468363a846f076",
            "is_error": false,
            "name": "\u043b\u0438\u0442\u0440"
        }
    },
    {
        "description": "",
        "group": {
            "description": "",
            "id": "2d2688011b934c258d366845e4780697",
            "is_error": false,
            "name": "\u0418\u043d\u0433\u0440\u0435\u0434\u0438\u0435\u043d\u0442\u044b"
        },
        "id": "da83c467e8cd444e834369e14f0c28fb",
        "is_error": false,
        "name": "\u041b\u0438\u043c\u043e\u043d\u043d\u044b\u0439 \u0441\u043e\u043a",
        "unit": {
            "base_unit": {
                "base_unit": null,
                "coefficient": 1,
                "description": "",
                "id": "f4f877c5af1e42508c303442b6aab3ad",
                "is_error": false,
                "name": "\u043c\u0438\u043b\u043b\u0438\u043b\u0438\u0442\u0440"
            },
            "coefficient": 1000,
            "description": "",
            "id": "52ef51fda1d34027b3468363a846f076",
            "is_error": false,
            "name": "\u043b\u0438\u0442\u0440"
        }
    },
    {
        "description": "",
        "group": {
            "description": "",
            "id": "2d2688011b934c258d366845e4780697",
            "is_error": false,
            "name": "\u0418\u043d\u0433\u0440\u0435\u0434\u0438\u0435\u043d\u0442\u044b"
        },
        "id": "6a72041ffa54427e98ea85bede4aac5c",
        "is_error": false,
        "name": "\u0413\u043e\u0440\u0447\u0438\u0446\u0430 \u0434\u0438\u0436\u043e\u043d\u0441\u043a\u0430\u044f",
        "unit": {
            "base_unit": null,
            "coefficient": 1,
            "description": "",
            "id": "ea0f05b621084be1b533456e4058ccb1",
            "is_error": false,
            "name": "\u0433\u0440\u0430\u043c\u043c"
        }
    },
    {
        "description": "",
        "group": {
            "description": "",
            "id": "2d2688011b934c258d366845e4780697",
            "is_error": false,
            "name": "\u0418\u043d\u0433\u0440\u0435\u0434\u0438\u0435\u043d\u0442\u044b"
        },
        "id": "b3bfc1e07c4b48e2812f0c4abe588032",
        "is_error": false,
        "name": "\u0421\u0430\u0445\u0430\u0440\u043d\u0430\u044f \u043f\u0443\u0434\u0440\u0430",
        "unit": {
            "base_unit": null,
            "coefficient": 1,
            "description": "",
            "id": "ea0f05b621084be1b533456e4058ccb1",
            "is_error": false,
            "name": "\u0433\u0440\u0430\u043c\u043c"
        }
    },
    {
        "description": "",
        "group": {
            "description": "",
            "id": "2d2688011b934c258d366845e4780697",
            "is_error": false,
            "name": "\u0418\u043d\u0433\u0440\u0435\u0434\u0438\u0435\u043d\u0442\u044b"
        },
        "id": "28243cd8af0946359d91b502b27a09a6",
        "is_error": false,
        "name": "\u0412\u0430\u043d\u0438\u043b\u0438\u0438\u043d",
        "unit": {
            "base_unit": null,
            "coefficient": 1,
            "description": "",
            "id": "ea0f05b621084be1b533456e4058ccb1",
            "is_error": false,
            "name": "\u0433\u0440\u0430\u043c\u043c"
        }
    },
    {
        "description": "",
        "group": {
            "description": "",
            "id": "2d2688011b934c258d366845e4780697",
            "is_error": false,
            "name": "\u0418\u043d\u0433\u0440\u0435\u0434\u0438\u0435\u043d\u0442\u044b"
        },
        "id": "fc876452d2284f0c89df92bb29b8f49f",
        "is_error": false,
        "name": "\u041a\u043e\u0440\u0438\u0446\u0430",
        "unit": {
            "base_unit": null,
            "coefficient": 1,
            "description": "",
            "id": "ea0f05b621084be1b533456e4058ccb1",
            "is_error": false,
            "name": "\u0433\u0440\u0430\u043c\u043c"
        }
    },
    {
        "description": "",
        "group": {
            "description": "",
            "id": "2d2688011b934c258d366845e4780697",
            "is_error": false,
            "name": "\u0418\u043d\u0433\u0440\u0435\u0434\u0438\u0435\u043d\u0442\u044b"
        },
        "id": "0cc2a345441042ffbd175f193fc57bde",
        "is_error": false,
        "name": "\u041a\u0430\u043a\u0430\u043e",
        "unit": {
            "base_unit": {
                "base_unit": null,
                "coefficient": 1,
                "description": "",
                "id": "7075b086851b4a4da0d61654e1614d14",
                "is_error": false,
                "name": "\u0433\u0440\u0430\u043c\u043c"
            },
            "coefficient": 1000,
            "description": "",
            "id": "570741618e994d1a845def2e717522d4",
            "is_error": false,
            "name": "\u043a\u0438\u043b\u043b\u043e\u0433\u0440\u0430\u043c\u043c"
        }
    }
]