{
    "description": "",
    "group": {
        "description": "",
        "id": "47df72ecface4b7583d025c85b461ff8",
        "is_error": false,
        "name": "\u0418\u043d\u0433\u0440\u0435\u0434\u0438\u0435\u043d\u0442\u044b"
    },
    "id": "438bcae4aa4f40f78f616a2f9bd55ef5",
    "is_error": false,
    "name": "\u041c\u0443\u043a\u0430 \u043f\u0448\u0435\u043d\u0438\u0447\u043d\u0430\u044f",
    "unit": {
        "base_unit": {
            "base_unit": null,
            "coefficient": 1,
            "description": "",
            "id": "7138b20e45ff4151a3b938a0f15099b9",
            "is_error": false,
            "name": "\u0433\u0440\u0430\u043c\u043c"
        },
        "coefficient": 1000,
        "description": "",
        "id": "0f9798364d514f979d9eba83edacda00",
        "is_error": false,
        "name": "\u043a\u0438\u043b\u043b\u043e\u0433\u0440\u0430\u043c\u043c"
    }
}